
<annotation>
    <folder>images</folder>
    <filename>hard_hat_workers553.png</filename>
    <size>
        <width>415</width>
        <height>416</height>
        <depth>3</depth>
    </size>
    <segmented>0</segmented>
    <object>
        <name>helmet</name>
        <pose>Unspecified</pose>
        <truncated>0</truncated>
        <occluded>0</occluded>
        <difficult>0</difficult>
        <bndbox>
            <xmin>161</xmin>
            <ymin>226</ymin>
            <xmax>179</xmax>
            <ymax>246</ymax>
        </bndbox>
    </object>
    <object>
        <name>helmet</name>
        <pose>Unspecified</pose>
        <truncated>0</truncated>
        <occluded>0</occluded>
        <difficult>0</difficult>
        <bndbox>
            <xmin>290</xmin>
            <ymin>185</ymin>
            <xmax>308</xmax>
            <ymax>203</ymax>
        </bndbox>
    </object>
    <object>
        <name>helmet</name>
        <pose>Unspecified</pose>
        <truncated>0</truncated>
        <occluded>0</occluded>
        <difficult>0</difficult>
        <bndbox>
            <xmin>200</xmin>
            <ymin>19</ymin>
            <xmax>213</xmax>
            <ymax>33</ymax>
        </bndbox>
    </object>
    <object>
        <name>helmet</name>
        <pose>Unspecified</pose>
        <truncated>0</truncated>
        <occluded>0</occluded>
        <difficult>0</difficult>
        <bndbox>
            <xmin>194</xmin>
            <ymin>123</ymin>
            <xmax>208</xmax>
            <ymax>140</ymax>
        </bndbox>
    </object>
    <object>
        <name>helmet</name>
        <pose>Unspecified</pose>
        <truncated>0</truncated>
        <occluded>0</occluded>
        <difficult>0</difficult>
        <bndbox>
            <xmin>384</xmin>
            <ymin>185</ymin>
            <xmax>402</xmax>
            <ymax>203</ymax>
        </bndbox>
    </object>
</annotation>